{
  "id": "ProfileDropdown.Component",
  "configId": "ProfileDropdown.Configuration.json",
  "menuItems": [
    {
      "id": "profile",
      "label": "My Profile",
      "icon": "👤",
      "action": "navigate",
      "type": "route",
      "target": "/profile",
      "visible": true
    },
    {
      "id": "my-books",
      "label": "My Books",
      "icon": "📚",
      "action": "navigate",
      "type": "route",
      "target": "/my-books",
      "visible": true
    },
    {
      "id": "reading-list",
      "label": "Reading List",
      "icon": "📖",
      "action": "navigate",
      "type": "route",
      "target": "/reading-list",
      "visible": true
    },
    {
      "id": "friends",
      "label": "Friends",
      "icon": "👥",
      "action": "navigate",
      "type": "route",
      "target": "/friends",
      "visible": true
    },
    {
      "id": "divider-1",
      "type": "divider",
      "visible": true
    },
    {
      "id": "settings",
      "label": "Settings",
      "icon": "⚙️",
      "action": "navigate",
      "type": "route",
      "target": "/settings",
      "visible": true
    },
    {
      "id": "divider-2",
      "type": "divider",
      "visible": true
    },
    {
      "id": "logout",
      "label": "Logout",
      "icon": "🚪",
      "action": "logout",
      "type": "action",
      "variant": "danger",
      "visible": true
    }
  ],
  "schema": {
    "menuItems": {
      "type": "array",
      "required": true,
      "description": "Array of menu items to display in the dropdown",
      "itemSchema": {
        "id": {
          "type": "string",
          "required": true,
          "description": "Unique identifier for the menu item"
        },
        "label": {
          "type": "string",
          "required": false,
          "description": "Display text for the item (not required for dividers)"
        },
        "icon": {
          "type": "string",
          "required": false,
          "description": "Emoji or icon to display"
        },
        "action": {
          "type": "string",
          "required": false,
          "enum": ["navigate", "logout"],
          "description": "Action type to perform"
        },
        "type": {
          "type": "string",
          "required": true,
          "enum": ["route", "action", "divider"],
          "description": "Type of menu item: route (navigation), action (custom action), divider (separator)"
        },
        "target": {
          "type": "string",
          "required": false,
          "description": "Navigation target path (required when type is route)"
        },
        "variant": {
          "type": "string",
          "required": false,
          "enum": ["default", "danger"],
          "description": "Visual variant of the item"
        },
        "visible": {
          "type": "boolean",
          "required": false,
          "default": true,
          "description": "Whether the item is visible"
        }
      }
    }
  },
  "behavior": {
    "closeOnClick": true,
    "closeOnClickOutside": true
  }
}
